{"_via_settings":{"ui":{"annotation_editor_height":70,"annotation_editor_fontsize":0.8,"leftsidebar_width":18,"image_grid":{"img_height":80,"rshape_fill":"none","rshape_fill_opacity":0.3,"rshape_stroke":"yellow","rshape_stroke_width":2,"show_region_shape":true,"show_image_policy":"all"},"image":{"region_label":"__via_region_id__","region_color":"__via_default_region_color__","region_label_font":"10px Sans","on_image_annotation_editor_placement":"NEAR_REGION"}},"core":{"buffer_size":18,"filepath":{},"default_filepath":""},"project":{"name":"11p0023"}},"_via_img_metadata":{"11P0023 Data_Sheet.png192749":{"filename":"11P0023 Data_Sheet.png","size":192749,"regions":[{"shape_attributes":{"name":"rect","x":262,"y":530,"width":230,"height":34},"region_attributes":{"print_text":"no.mot"}},{"shape_attributes":{"name":"rect","x":275,"y":570,"width":230,"height":25},"region_attributes":{"print_text":"no.tur"}},{"shape_attributes":{"name":"rect","x":271,"y":597,"width":101,"height":29},"region_attributes":{"print_text":"pump"}},{"shape_attributes":{"name":"rect","x":521,"y":530,"width":304,"height":29},"region_attributes":{"print_text":"for pump"}},{"shape_attributes":{"name":"rect","x":533,"y":573,"width":307,"height":20},"region_attributes":{"print_text":"for pump it"}},{"shape_attributes":{"name":"rect","x":879,"y":470,"width":87,"height":27},"region_attributes":{"print_text":"site"}},{"shape_attributes":{"name":"rect","x":900,"y":499,"width":107,"height":29},"region_attributes":{"print_text":"service"}},{"shape_attributes":{"name":"rect","x":828,"y":598,"width":155,"height":24},"region_attributes":{"print_text":"size"}},{"shape_attributes":{"name":"rect","x":1041,"y":535,"width":165,"height":25},"region_attributes":{"print_text":"provided"}},{"shape_attributes":{"name":"rect","x":1047,"y":570,"width":157,"height":22},"region_attributes":{"print_text":"provided by"}},{"shape_attributes":{"name":"rect","x":1376,"y":539,"width":90,"height":25},"region_attributes":{"print_text":"mto"}}],"file_attributes":{}}},"_via_attributes":{"region":{"print_text":{"type":"text","description":"name","default_value":""}},"file":{}}}