{"_via_settings":{"ui":{"annotation_editor_height":30,"annotation_editor_fontsize":0.8,"leftsidebar_width":18,"image_grid":{"img_height":80,"rshape_fill":"none","rshape_fill_opacity":0.3,"rshape_stroke":"yellow","rshape_stroke_width":2,"show_region_shape":true,"show_image_policy":"all"},"image":{"region_label":"__via_region_id__","region_color":"__via_default_region_color__","region_label_font":"10px Sans","on_image_annotation_editor_placement":"NEAR_REGION"}},"core":{"buffer_size":18,"filepath":{},"default_filepath":""},"project":{"name":"11p0022"}},"_via_img_metadata":{"11P0022 Data_Sheet.png193168":{"filename":"11P0022 Data_Sheet.png","size":193168,"regions":[{"shape_attributes":{"name":"rect","x":264,"y":506,"width":80,"height":34},"region_attributes":{"print_text":"unit"}},{"shape_attributes":{"name":"rect","x":268,"y":537,"width":217,"height":27},"region_attributes":{"print_text":"no mot"}},{"shape_attributes":{"name":"rect","x":264,"y":575,"width":230,"height":20},"region_attributes":{"print_text":"no tur"}},{"shape_attributes":{"name":"rect","x":271,"y":600,"width":101,"height":27},"region_attributes":{"print_text":"pump"}},{"shape_attributes":{"name":"rect","x":514,"y":532,"width":311,"height":29},"region_attributes":{"print_text":"for pump"}},{"shape_attributes":{"name":"rect","x":535,"y":571,"width":298,"height":22},"region_attributes":{"print_text":"for pump it"}},{"shape_attributes":{"name":"rect","x":902,"y":501,"width":107,"height":29},"region_attributes":{"print_text":"service"}},{"shape_attributes":{"name":"rect","x":835,"y":598,"width":148,"height":31},"region_attributes":{"print_text":"size"}},{"shape_attributes":{"name":"rect","x":1038,"y":533,"width":168,"height":31},"region_attributes":{"print_text":"provided"}},{"shape_attributes":{"name":"rect","x":1041,"y":568,"width":170,"height":27},"region_attributes":{"print_text":"provided by"}},{"shape_attributes":{"name":"rect","x":1324,"y":504,"width":233,"height":22},"region_attributes":{"print_text":"no of "}},{"shape_attributes":{"name":"rect","x":1378,"y":535,"width":90,"height":36},"region_attributes":{"print_text":"mt"}},{"shape_attributes":{"name":"rect","x":1371,"y":568,"width":101,"height":31},"region_attributes":{"print_text":"mtd"}}],"file_attributes":{}}},"_via_attributes":{"region":{"print_text":{"type":"text","description":"name","default_value":""}},"file":{}}}