{"_via_settings":{"ui":{"annotation_editor_height":65,"annotation_editor_fontsize":0.7000000000000001,"leftsidebar_width":18,"image_grid":{"img_height":80,"rshape_fill":"none","rshape_fill_opacity":0.3,"rshape_stroke":"yellow","rshape_stroke_width":2,"show_region_shape":true,"show_image_policy":"all"},"image":{"region_label":"__via_region_id__","region_color":"__via_default_region_color__","region_label_font":"10px Sans","on_image_annotation_editor_placement":"NEAR_REGION"}},"core":{"buffer_size":18,"filepath":{},"default_filepath":""},"project":{"name":"11p22"}},"_via_img_metadata":{"11P22.png200805":{"filename":"11P22.png","size":200805,"regions":[{"shape_attributes":{"name":"rect","x":200,"y":472,"width":97,"height":32},"region_attributes":{"print_text":"service"}},{"shape_attributes":{"name":"rect","x":887,"y":365,"width":269,"height":35},"region_attributes":{"print_text":"no of p"}},{"shape_attributes":{"name":"rect","x":892,"y":398,"width":289,"height":33},"region_attributes":{"print_text":"no of m"}},{"shape_attributes":{"name":"rect","x":894,"y":435,"width":103,"height":27},"region_attributes":{"print_text":"item"}},{"shape_attributes":{"name":"rect","x":895,"y":474,"width":161,"height":23},"region_attributes":{"print_text":"provided"}},{"shape_attributes":{"name":"rect","x":895,"y":506,"width":174,"height":32},"region_attributes":{"print_text":"man"}},{"shape_attributes":{"name":"rect","x":898,"y":541,"width":149,"height":38},"region_attributes":{"print_text":"size"}}],"file_attributes":{}}},"_via_attributes":{"region":{"print_text":{"type":"text","description":"name","default_value":""}},"file":{}}}